guira/__init__.py
guira/controllers.py
guira/curves.py
guira/guira_exceptions.py
guira/remoteApi.dll
guira/remoteApi.so
guira/robot.py
guira/scene.py
guira/sensors.py
guira/sim.py
guira/simConst.py
guira/utils.py
guira-0.1.0.dist-info/LICENSE
guira-0.1.0.dist-info/METADATA
guira-0.1.0.dist-info/WHEEL
guira-0.1.0.dist-info/RECORD
