Metadata-Version: 2.1
Name: guira
Version: 0.1.0
Summary: Guira is a Python Library for Robotic Simulation with CoppeliaSim (EDU 4.3.0).
Author: Mateus Assis
Author-email: mateus.d.assis.silva@gmail.com
Requires-Python: >=3.9,<4.0
Classifier: Programming Language :: Python :: 3
Classifier: Programming Language :: Python :: 3.9
Classifier: Programming Language :: Python :: 3.10
Classifier: Programming Language :: Python :: 3.11
Requires-Dist: numpy (>=1.23.3,<2.0.0)
Requires-Dist: pandas (>=1.5.0,<2.0.0)
